wagtail_tenants/__init__.py
wagtail_tenants/admin.py
wagtail_tenants/apps.py
wagtail_tenants/backends.py
wagtail_tenants/customers/__init__.py
wagtail_tenants/customers/admin.py
wagtail_tenants/customers/apps.py
wagtail_tenants/customers/migrations/0001_initial.py
wagtail_tenants/customers/migrations/0002_clientbackup.py
wagtail_tenants/customers/migrations/0003_alter_clientbackup_created_at.py
wagtail_tenants/customers/migrations/0004_auto_20230321_1407.py
wagtail_tenants/customers/migrations/__init__.py
wagtail_tenants/customers/models.py
wagtail_tenants/customers/tests.py
wagtail_tenants/customers/views.py
wagtail_tenants/db/__init__.py
wagtail_tenants/db/db_backup_connector.py
wagtail_tenants/decorators.py
wagtail_tenants/forms.py
wagtail_tenants/management/__init__.py
wagtail_tenants/management/commands/create_tenant.py
wagtail_tenants/management/commands/create_tenant_superuser.py
wagtail_tenants/management/commands/dbbackup_tenant.py
wagtail_tenants/management/commands/migrate_schemas.py
wagtail_tenants/middleware/main.py
wagtail_tenants/migrations/0001_initial.py
wagtail_tenants/migrations/__init__.py
wagtail_tenants/models.py
wagtail_tenants/panels.py
wagtail_tenants/routers.py
wagtail_tenants/services.py
wagtail_tenants/signals.py
wagtail_tenants/templates/wagtail_tenants/admin/link.html
wagtail_tenants/templates/wagtailadmin/home/tenant_panel.html
wagtail_tenants/templates/wagtailusers/groups/confirm_delete.html
wagtail_tenants/templates/wagtailusers/groups/create.html
wagtail_tenants/templates/wagtailusers/groups/edit.html
wagtail_tenants/templates/wagtailusers/groups/includes/formatted_permissions.html
wagtail_tenants/templates/wagtailusers/groups/includes/group_form_js.html
wagtail_tenants/templates/wagtailusers/groups/includes/page_permissions_form.html
wagtail_tenants/templates/wagtailusers/groups/includes/page_permissions_formset.html
wagtail_tenants/templates/wagtailusers/groups/index.html
wagtail_tenants/templates/wagtailusers/groups/results.html
wagtail_tenants-0.1.11.dist-info/WHEEL
wagtail_tenants-0.1.11.dist-info/METADATA
wagtail_tenants-0.1.11.dist-info/RECORD
