Metadata-Version: 2.1
Name: wagtail-tenants
Version: 0.1.11
Summary: Adds multitenancy based on django_tenants to wagtail cms
Home-page: https://wagtail-tenants.readthedocs.io/en/latest/
License: MIT
Author: Boris Brue
Author-email: boris@zuckersalzundpfeffer.de
Requires-Python: >=3.9.0,<4.0.0
Classifier: License :: OSI Approved :: MIT License
Classifier: Programming Language :: Python :: 3
Classifier: Programming Language :: Python :: 3.10
Classifier: Programming Language :: Python :: 3.9
Provides-Extra: docs
Requires-Dist: django-dbbackup (>=3.3.0,<4.0.0)
Requires-Dist: django-tenants (>=3.3.4,<4.0.0)
Project-URL: Repository, https://github.com/borisbrue/wagtail-tenants
